{
    "Food": [
      {
        "FoodId": "7",
        "FoodName": "Vegetarian Lotus Flower Rice",
        "FoodRecepiee": "Lotus Flower, Rice",
        "FoodPrice": "18",
        "FoodCategory": "veg",
        "FoodThumb": "https://images.foody.vn/images/bc1.jpg"
      },
      {
        "FoodId": "8",
        "FoodName": "Vegetarian papaya salad",
        "FoodRecepiee": "papaya",
        "FoodPrice": "15",
        "FoodCategory": "veg",
        "FoodThumb": "https://file.hstatic.net/200000033118/file/ca_rot_tron_sa_1b184ae357bd4d97aadcb94c97eecd11_grande.jpg"
      },
      {
        "FoodId": "9",
        "FoodName": "Vegetarian noodles",
        "FoodRecepiee": "noodles, vegetable",
        "FoodPrice": "22",
        "FoodCategory": "veg",
        "FoodThumb": "https://afamilycdn.com/150157425591193600/2021/1/4/1331498651095439843752038585580396512775317o-1609730924227527241730.jpg"
      },
      {
        "FoodId": "10",
        "FoodName": "Stir-fried Vegetables with Vegetarian Sauce",
        "FoodRecepiee": "Vegetables",
        "FoodPrice": "25",
        "FoodCategory": "veg",
        "FoodThumb": "https://cdn.tgdd.vn/2021/05/CookRecipe/Avatar/rau-cu-xao-chay-thumbnail.jpg"
      },
      {
        "FoodId": "11",
        "FoodName": "JELLY YOGURT",
        "FoodRecepiee": "YOGURT, Strawberry",
        "FoodPrice": "17",
        "FoodCategory": "veg",
        "FoodThumb": "https://cdn.daynauan.info.vn/wp-content/uploads/2019/05/sua-chua-deo.jpg"
      },
      {
        "FoodId": "12",
        "FoodName": "Crispy tofu",
        "FoodRecepiee": "tofu",
        "FoodPrice": "11",
        "FoodCategory": "veg",
        "FoodThumb": "https://ichef.bbci.co.uk/news/640/cpsprodpb/105AC/production/_114888966_bbf67a04-8540-4577-867e-b3fff1c745da.jpg"
      },
      {
        "FoodId": "19",
        "FoodName": "Bun cha Hanoi",
        "FoodRecepiee": "Rice noodle, barbecue,spring rolls",
        "FoodPrice": "17",
        "FoodCategory": "non-veg",
        "FoodThumb": "https://www.thatlangon.com/wp-content/uploads/2020/09/bun-cha6.jpg"
      },
      {
        "FoodId": "20",
        "FoodName": "Hanoi bread",
        "FoodRecepiee": "bread, barbecue, vegetable",
        "FoodPrice": "21",
        "FoodCategory": "non-veg",
        "FoodThumb": "https://images.foody.vn/res/g105/1046968/prof/s640x400/foody-upload-api-foody-mobile-20-200916132829.jpg"
      },
      {
        "FoodId": "21",
        "FoodName": "Grilled chopped fish",
        "FoodRecepiee": "fish,spices",
        "FoodPrice": "15",
        "FoodCategory": "non-veg",
        "FoodThumb": "https://tourism.hanoi.gov.vn/storage/cha-ca-la-vong-1.jpg"
      },
      {
        "FoodId": "22",
        "FoodName": "vermicelli with shrimp paste",
        "FoodRecepiee": "shrimp paste,vermicelli",
        "FoodPrice": "18",
        "FoodCategory": "non-veg",
        "FoodThumb": "https://dulich9.com/wp-content/uploads/2019/05/Mon-an-ngon-Ha-Noi-bun-dau-Mam-Tom.jpg"
      },
      {
        "FoodId": "23",
        "FoodName": "BBQ Chicken",
        "FoodRecepiee": "chicken, lemon",
        "FoodPrice": "26",
        "FoodCategory": "non-veg",
        "FoodThumb": "https://truyenhinhvov.qltns.mediacdn.vn/239964650902032384/2021/5/18/5601mondaklak5-1621309467477-16213094679061957399746.jpg"
      },
      {
        "FoodId": "24",
        "FoodName": "Steamed Broken Rice",
        "FoodRecepiee": "rice, rib, cha",
        "FoodPrice": "24",
        "FoodCategory": "non-veg",
        "FoodThumb": "https://storage.ctu.edu.vn/aunilo2018/images/Images/AUNILO2018/Food/cach-lam-nuoc-mam-an-com-tam.jpg"
      }
    ]
  }